csvtables/__init__.py
csvtables/csvtables.py
csvtables-0.4.0.dist-info/LICENSE
csvtables-0.4.0.dist-info/METADATA
csvtables-0.4.0.dist-info/WHEEL
csvtables-0.4.0.dist-info/entry_points.txt
csvtables-0.4.0.dist-info/top_level.txt
csvtables-0.4.0.dist-info/RECORD
