Metadata-Version: 2.1
Name: csvtables
Version: 0.4.0
Summary: Convert a CSV formatted input to a readable table in text
Author: Demetris Stavrou
Requires-Python: >=3.7
License-File: LICENSE
